README
setup.py
netsnmp/__init__.py
netsnmp/client.py
netsnmp/client_intf.c
netsnmp/tests/__init__.py
netsnmp/tests/test.py
python3_netsnmp.egg-info/PKG-INFO
python3_netsnmp.egg-info/SOURCES.txt
python3_netsnmp.egg-info/dependency_links.txt
python3_netsnmp.egg-info/top_level.txt