Metadata-Version: 1.0
Name: python3-netsnmp
Version: 1.0a1
Summary: The Net-SNMP Python Interface
Home-page: http://www.net-snmp.org
Author: G. S. Marzot
Author-email: giovanni.marzot@sparta.com
License: BSD
Platform: UNKNOWN
